amirm_bot_utils/__init__.py
amirm_bot_utils/text.py
amirm_bot_utils-0.1.6.dist-info/METADATA
amirm_bot_utils-0.1.6.dist-info/WHEEL
amirm_bot_utils-0.1.6.dist-info/top_level.txt
amirm_bot_utils-0.1.6.dist-info/RECORD
